proto_inspect.py
proto_inspect-0.3.dist-info/LICENSE
proto_inspect-0.3.dist-info/METADATA
proto_inspect-0.3.dist-info/WHEEL
proto_inspect-0.3.dist-info/top_level.txt
proto_inspect-0.3.dist-info/RECORD
